config/__init__.py
config/asgi.py
config/custom_config.py
config/settings.py
config/urls.py
config/wsgi.py
main/__init__.py
main/admin.py
main/apps.py
main/urls.py
main/migrations/__init__.py
main/models/__init__.py
main/models/base.py
shax_dev-0.2.dist-info/METADATA
shax_dev-0.2.dist-info/WHEEL
shax_dev-0.2.dist-info/top_level.txt
shax_dev-0.2.dist-info/RECORD
